CHANGES.txt
LICENSE.txt
MANIFEST.in
README.rst
setup.py
pyx509/__init__.py
pyx509/commands.py
pyx509/compat.py
pyx509/models.py
pyx509/pkcs7/__init__.py
pyx509/pkcs7/debug.py
pyx509/pkcs7/digest.py
pyx509/pkcs7/pkcs7_decoder.py
pyx509/pkcs7/tstamp_helper.py
pyx509/pkcs7/verifier.py
pyx509/pkcs7/asn1_models/DSA.py
pyx509/pkcs7/asn1_models/RSA.py
pyx509/pkcs7/asn1_models/TST_info.py
pyx509/pkcs7/asn1_models/X509_certificate.py
pyx509/pkcs7/asn1_models/__init__.py
pyx509/pkcs7/asn1_models/att_certificate_v2.py
pyx509/pkcs7/asn1_models/certificate_extensions.py
pyx509/pkcs7/asn1_models/crl.py
pyx509/pkcs7/asn1_models/decoder_workarounds.py
pyx509/pkcs7/asn1_models/digest_info.py
pyx509/pkcs7/asn1_models/general_types.py
pyx509/pkcs7/asn1_models/oid.py
pyx509/pkcs7/asn1_models/pkcs_signed_data.py
pyx509/pkcs7/asn1_models/tools.py
pyx509/test/__init__.py
pyx509/test/test_cert.py
pyx509/test/test_simple.py
pyx509/test/test_utf8.py
pyx509/test/data/cades-xl.csig
pyx509/test/data/test_certificate.der
pyx509/test/data/test_certificate.txt
pyx509/test/data/test_certificate_old.txt
pyx509/test/data/test_sig3.der
pyx509/test/data/test_sig3.txt
pyx509/test/data/test_sig4.der
pyx509/test/data/test_sig4.txt
pyx509/test/data/test_signature.der
pyx509/test/data/test_signature.txt
pyx509/test/data/test_timestamp.der
pyx509/test/data/test_timestamp.txt
pyx509/test/data/test_timestamp_info.txt
pyx509_ph4.egg-info/PKG-INFO
pyx509_ph4.egg-info/SOURCES.txt
pyx509_ph4.egg-info/dependency_links.txt
pyx509_ph4.egg-info/entry_points.txt
pyx509_ph4.egg-info/not-zip-safe
pyx509_ph4.egg-info/requires.txt
pyx509_ph4.egg-info/top_level.txt