Metadata-Version: 1.0
Name: pyx509-ph4
Version: 0.2.2
Summary: Parse x509v3 certificates and PKCS7 signatures
Home-page: https://github.com/ph4r05/pyx509
Author: ph4r05
Author-email: ph4r05@gmail.com
License:     This library is free software; you can redistribute it and/or
